MANIFEST.in
README.md
setup.py
src/s3repo/__init__.py
src/s3repo/command.py
src/s3repo/field_set.py
src/s3repo/packages_file.py
src/s3repo/release_file.py
src/s3repo/repo.py
src/s3repo.egg-info/PKG-INFO
src/s3repo.egg-info/SOURCES.txt
src/s3repo.egg-info/dependency_links.txt
src/s3repo.egg-info/entry_points.txt
src/s3repo.egg-info/top_level.txt