Metadata-Version: 1.1
Name: s3repo
Version: 1.2
Summary: A tool to manage simple Debian repositories in S3
Home-page: http://github.com/crewjam/s3repo
Author: Ross Kinder
Author-email: ross+czNyZXBv@kndr.org
License: BSD
Platform: UNKNOWN
Requires: boto
